monazco/__init__.py
monazco/board.py
monazco/constants.py
monazco/gymlike_env.py
monazco/nodes.py
monazco/play.py
monazco/utils/__init__.py
monazco/utils/errors.py
monazco/utils/functions.py
monazco-0.1.1.dist-info/METADATA
monazco-0.1.1.dist-info/WHEEL
monazco-0.1.1.dist-info/RECORD
